pythoncli/__init__.py
pythoncli/__main__.py
pythoncli/classmodule.py
pythoncli/effectsmodule.py
pythoncli/funcmodule.py
pythoncli/generatingmodule.py
pythoncli/loadingmodule.py
pythoncli/resamplemodule.py
pythoncli/supereffectmodule.py
pythoncli-1.0.2.dist-info/METADATA
pythoncli-1.0.2.dist-info/RECORD
pythoncli-1.0.2.dist-info/WHEEL
pythoncli-1.0.2.dist-info/entry_points.txt
pythoncli-1.0.2.dist-info/top_level.txt
